yaks/__init__.py
yaks/admin.py
yaks/encoding.py
yaks/entry.py
yaks/exceptions.py
yaks/logger.py
yaks/path.py
yaks/selector.py
yaks/value.py
yaks/workspace.py
yaks/yaks.py
yaks-0.3.0.post1.dist-info/LICENSE
yaks-0.3.0.post1.dist-info/METADATA
yaks-0.3.0.post1.dist-info/WHEEL
yaks-0.3.0.post1.dist-info/top_level.txt
yaks-0.3.0.post1.dist-info/RECORD
